convert.py
nexusconverter-0.0.3.dist-info/METADATA
nexusconverter-0.0.3.dist-info/WHEEL
nexusconverter-0.0.3.dist-info/top_level.txt
nexusconverter-0.0.3.dist-info/RECORD
