Metadata-Version: 2.1
Name: nexusconverter
Version: 0.0.3
Summary: 将 PyTorch 模型转换为 Nexus 代码
Home-page: UNKNOWN
Author: Guo Shuai
Author-email: gs0801@foxmail.com
License: UNKNOWN
Platform: UNKNOWN
Requires-Python: >=3.6, <4
Requires-Dist: parse
